Tareas/Single_Cycle_RISCV/InstructionMemory.v
module InstructionMemory #(parameter ADD = 8) (
    input [31:0] Address,
    output [31:0] ReadData
);
    reg [31:0] ROM[(2**ADD)-1:0];
    localparam INSTRUCTION_COUNT = 21;  // Cambia según tu .hex

    initial begin
        $readmemh("instructions.hex", ROM);
    end

    assign ReadData = (Address >> 2) < INSTRUCTION_COUNT ? ROM[Address >> 2] : 32'hXXXXXXXX;

endmodule

Tareas/Single_Cycle_RISCV/InstructionMemory_tb.v
`timescale 1ns / 1ps

module InstructionMemory_tb;
    // Parámetros del testbench
    parameter ADD = 8; // Mismo parámetro que el módulo
    
    // Señales del testbench
    reg [31:0] Address;
    wire [31:0] ReadData;
    integer i;
    
    // Instancia del módulo bajo prueba
    InstructionMemory #(.ADD(ADD)) uut (
        .Address(Address),
        .ReadData(ReadData)
    );
    
    initial begin
        $dumpfile("instruction_memory_wave.vcd");
        $dumpvars(0, InstructionMemory_tb);
        
        // Esperar a que la memoria se inicialice
        #5;
        
        $display("=== Prueba del módulo InstructionMemory ===");
        $display("Parámetro ADD = %0d (Memoria de %0d palabras)", ADD, 2**ADD);
        $display("Time\tAddress\t\tAddr>>2\tReadData\tHex");
        $display("-------------------------------------------------------");
        
        // Test 1: Direcciones alineadas (múltiplos de 4)
        $display("\n--- Prueba 1: Direcciones alineadas ---");
        for (i = 0; i < 20; i = i + 1) begin
            Address = i * 4; // Direcciones: 0, 4, 8, 12, 16, ...
            #10;
            $display("%0t\t%8h\t%3d\t%8h\t%h", 
                     $time, Address, Address>>2, ReadData, ReadData);
        end
        
        // Test 2: Direcciones específicas importantes
        $display("\n--- Prueba 2: Direcciones específicas ---");
        
        // Dirección 0 (primera instrucción)
        Address = 32'h00000000;
        #10;
        $display("PC=0x%h -> Instrucción=0x%h", Address, ReadData);
        
        // Dirección 4 (segunda instrucción)
        Address = 32'h00000004;
        #10;
        $display("PC=0x%h -> Instrucción=0x%h", Address, ReadData);
        
        // Dirección del medio
        Address = 32'h00000040; // Dirección 64 decimal
        #10;
        $display("PC=0x%h -> Instrucción=0x%h", Address, ReadData);
        
        // Última dirección válida
        Address = (2**ADD - 1) * 4;
        #10;
        $display("PC=0x%h -> Instrucción=0x%h (última dirección)", Address, ReadData);
        
        // Test 3: Verificar el comportamiento del shift
        $display("\n--- Prueba 3: Verificación del desplazamiento >>2 ---");
        Address = 32'h00000000; #10;
        $display("Address=0x%h -> Index=%0d -> Data=0x%h", Address, Address>>2, ReadData);
        
        Address = 32'h00000004; #10;
        $display("Address=0x%h -> Index=%0d -> Data=0x%h", Address, Address>>2, ReadData);
        
        Address = 32'h00000008; #10;
        $display("Address=0x%h -> Index=%0d -> Data=0x%h", Address, Address>>2, ReadData);
        
        // Test 4: Direcciones fuera de rango (opcional)
        $display("\n--- Prueba 4: Direcciones límite ---");
        Address = (2**ADD) * 4; // Fuera de rango
        #10;
        $display("Address=0x%h (fuera de rango) -> Data=0x%h", Address, ReadData);
        
        $display("\n=== Fin de pruebas ===");
        $finish;
    end
    
    // Monitor para cambios automáticos
    initial begin
        $monitor("Tiempo=%0t: Address=0x%h, ReadData=0x%h", 
                 $time, Address, ReadData);
    end
    
endmodule

Tareas/Single_Cycle_RISCV/simulation/questa/instruction_memory_wave.vcd
$date
	Wed May 28 08:26:31 2025
$end
$version
	Questa Intel Starter FPGA Edition Version 2023.3
$end
$timescale
	1ps
$end

$scope module InstructionMemory_tb $end
$var parameter 32 ! ADD $end
$var reg 32 " Address [31:0] $end
$var wire 1 # ReadData [31] $end
$var wire 1 $ ReadData [30] $end
$var wire 1 % ReadData [29] $end
$var wire 1 & ReadData [28] $end
$var wire 1 ' ReadData [27] $end
$var wire 1 ( ReadData [26] $end
$var wire 1 ) ReadData [25] $end
$var wire 1 * ReadData [24] $end
$var wire 1 + ReadData [23] $end
$var wire 1 , ReadData [22] $end
$var wire 1 - ReadData [21] $end
$var wire 1 . ReadData [20] $end
$var wire 1 / ReadData [19] $end
$var wire 1 0 ReadData [18] $end
$var wire 1 1 ReadData [17] $end
$var wire 1 2 ReadData [16] $end
$var wire 1 3 ReadData [15] $end
$var wire 1 4 ReadData [14] $end
$var wire 1 5 ReadData [13] $end
$var wire 1 6 ReadData [12] $end
$var wire 1 7 ReadData [11] $end
$var wire 1 8 ReadData [10] $end
$var wire 1 9 ReadData [9] $end
$var wire 1 : ReadData [8] $end
$var wire 1 ; ReadData [7] $end
$var wire 1 < ReadData [6] $end
$var wire 1 = ReadData [5] $end
$var wire 1 > ReadData [4] $end
$var wire 1 ? ReadData [3] $end
$var wire 1 @ ReadData [2] $end
$var wire 1 A ReadData [1] $end
$var wire 1 B ReadData [0] $end
$var integer 32 C i $end

$scope module uut $end
$var parameter 32 D ADD $end
$var wire 1 E Address [31] $end
$var wire 1 F Address [30] $end
$var wire 1 G Address [29] $end
$var wire 1 H Address [28] $end
$var wire 1 I Address [27] $end
$var wire 1 J Address [26] $end
$var wire 1 K Address [25] $end
$var wire 1 L Address [24] $end
$var wire 1 M Address [23] $end
$var wire 1 N Address [22] $end
$var wire 1 O Address [21] $end
$var wire 1 P Address [20] $end
$var wire 1 Q Address [19] $end
$var wire 1 R Address [18] $end
$var wire 1 S Address [17] $end
$var wire 1 T Address [16] $end
$var wire 1 U Address [15] $end
$var wire 1 V Address [14] $end
$var wire 1 W Address [13] $end
$var wire 1 X Address [12] $end
$var wire 1 Y Address [11] $end
$var wire 1 Z Address [10] $end
$var wire 1 [ Address [9] $end
$var wire 1 \ Address [8] $end
$var wire 1 ] Address [7] $end
$var wire 1 ^ Address [6] $end
$var wire 1 _ Address [5] $end
$var wire 1 ` Address [4] $end
$var wire 1 a Address [3] $end
$var wire 1 b Address [2] $end
$var wire 1 c Address [1] $end
$var wire 1 d Address [0] $end
$var wire 1 # ReadData [31] $end
$var wire 1 $ ReadData [30] $end
$var wire 1 % ReadData [29] $end
$var wire 1 & ReadData [28] $end
$var wire 1 ' ReadData [27] $end
$var wire 1 ( ReadData [26] $end
$var wire 1 ) ReadData [25] $end
$var wire 1 * ReadData [24] $end
$var wire 1 + ReadData [23] $end
$var wire 1 , ReadData [22] $end
$var wire 1 - ReadData [21] $end
$var wire 1 . ReadData [20] $end
$var wire 1 / ReadData [19] $end
$var wire 1 0 ReadData [18] $end
$var wire 1 1 ReadData [17] $end
$var wire 1 2 ReadData [16] $end
$var wire 1 3 ReadData [15] $end
$var wire 1 4 ReadData [14] $end
$var wire 1 5 ReadData [13] $end
$var wire 1 6 ReadData [12] $end
$var wire 1 7 ReadData [11] $end
$var wire 1 8 ReadData [10] $end
$var wire 1 9 ReadData [9] $end
$var wire 1 : ReadData [8] $end
$var wire 1 ; ReadData [7] $end
$var wire 1 < ReadData [6] $end
$var wire 1 = ReadData [5] $end
$var wire 1 > ReadData [4] $end
$var wire 1 ? ReadData [3] $end
$var wire 1 @ ReadData [2] $end
$var wire 1 A ReadData [1] $end
$var wire 1 B ReadData [0] $end
$upscope $end
$upscope $end
$enddefinitions $end
#0
$dumpvars
bx "
b1000 !
b1000 D
bx C
xB
xA
x@
x?
x>
x=
x<
x;
x:
x9
x8
x7
x6
x5
x4
x3
x2
x1
x0
x/
x.
x-
x,
x+
x*
x)
x(
x'
x&
x%
x$
x#
xd
xc
xb
xa
x`
x_
x^
x]
x\
x[
xZ
xY
xX
xW
xV
xU
xT
xS
xR
xQ
xP
xO
xN
xM
xL
xK
xJ
xI
xH
xG
xF
xE
$end
#5000
b0 C
b0 "
0d
0c
0b
0a
0`
0_
0^
0]
0\
0[
0Z
0Y
0X
0W
0V
0U
0T
0S
0R
0Q
0P
0O
0N
0M
0L
0K
0J
0I
0H
0G
0F
0E
1B
1A
0@
0?
1>
0=
0<
0;
1:
09
08
07
06
05
04
03
02
01
00
0/
1.
0-
1,
0+
0*
0)
0(
0'
0&
0%
0$
0#
#15000
b1 C
b100 "
1b
1;
0.
1+
#25000
b10 C
b1000 "
0b
1a
19
13
12
1.
1-
0+
1*
1)
1(
1'
1&
1%
1$
1#
#35000
b11 C
b1100 "
1b
1=
0;
0:
15
14
11
0.
0,
0*
0)
0(
0'
0&
0%
0$
0#
#45000
b100 C
b10000 "
0b
0a
1`
1;
16
01
0-
1,
#55000
b101 C
b10100 "
1b
06
05
04
02
11
#65000
b110 C
b11000 "
0b
1a
0>
1<
0;
09
17
1.
1-
1)
#75000
b111 C
b11100 "
1b
1>
0<
19
07
15
12
01
0.
0-
0)
#85000
b1000 C
b100000 "
0b
0a
0`
1_
0>
1<
09
18
05
03
02
11
0,
#95000
b1001 C
b100100 "
1b
1>
0=
0<
1;
19
08
01
#105000
b1010 C
b101000 "
0b
1a
1=
0;
15
13
12
11
1-
#115000
b1011 C
b101100 "
1b
1;
1:
05
03
02
1.
0-
1,
#125000
b1100 C
b110000 "
0b
0a
1`
13
12
0.
1-
0,
1$
#135000
b1101 C
b110100 "
1b
0>
0;
0:
17
15
01
1.
1,
1(
0$
#145000
b1110 C
b111000 "
0b
1a
0=
1:
09
07
03
02
0.
0-
0,
1)
#155000
b1111 C
b111100 "
1b
1>
1=
1;
0:
18
05
12
1.
1,
0)
0(
#165000
b10000 C
b1000000 "
0b
0a
0`
0_
1^
1@
1?
0>
1<
1:
08
02
0.
0,
1+
#175000
b10001 C
b1000100 "
1b
0@
0?
1>
0=
0<
0;
1.
0+
#185000
b10010 C
b1001000 "
0b
1a
1=
12
1+
#195000
b10011 C
b1001100 "
1b
0>
0:
15
13
0.
1-
0+
1)
#205000
b10100 C
b0 "
0b
0a
0^
1>
0=
1:
05
03
02
1.
0-
1,
0)
#215000
b100 "
1b
1;
0.
1+
#225000
b1000000 "
0b
1^
1@
1?
0>
1=
1<
0,
#235000
b1111111100 "
1b
1a
1`
1_
1]
1\
1[
xB
xA
x@
x?
x>
x=
x<
x;
x:
x9
x8
x7
x6
x5
x4
x3
x2
x1
x0
x/
x.
x-
x,
x+
x*
x)
x(
x'
x&
x%
x$
x#
#245000
b0 "
0b
0a
0`
0_
0^
0]
0\
0[
1B
1A
0@
0?
1>
0=
0<
0;
1:
09
08
07
06
05
04
03
02
01
00
0/
1.
0-
1,
0+
0*
0)
0(
0'
0&
0%
0$
0#
#255000
b100 "
1b
1;
0.
1+
#265000
b1000 "
0b
1a
19
13
12
1.
1-
0+
1*
1)
1(
1'
1&
1%
1$
1#
#275000
b10000000000 "
0a
1Z
xB
xA
x@
x?
x>
x=
x<
x;
x:
x9
x8
x7
x6
x5
x4
x3
x2
x1
x0
x/
x.
x-
x,
x+
x*
x)
x(
x'
x&
x%
x$
x#
